revtools/__init__.py
revtools/db_helper.py
revtools-0.1.4.dist-info/METADATA
revtools-0.1.4.dist-info/WHEEL
revtools-0.1.4.dist-info/top_level.txt
revtools-0.1.4.dist-info/RECORD
