Metadata-Version: 2.2
Name: revtools
Version: 0.1.4
Summary: Make your simple db with revtools!
Home-page: https://github.com/PcHelpdone/revtools
Author: Syed Ahmed Uddin
Author-email: revdevtools@gmail.com
Classifier: Programming Language :: Python :: 3
Classifier: License :: OSI Approved :: MIT License
Classifier: Operating System :: OS Independent
Requires-Dist: google-generativeai
Dynamic: author
Dynamic: author-email
Dynamic: classifier
Dynamic: description
Dynamic: description-content-type
Dynamic: home-page
Dynamic: requires-dist
Dynamic: summary
